spotify_gender_ex/__init__.py
spotify_gender_ex/__main__.py
spotify_gender_ex/appstore.py
spotify_gender_ex/downloader.py
spotify_gender_ex/genderex.py
spotify_gender_ex/gh_issue.py
spotify_gender_ex/lang_file.py
spotify_gender_ex/notify.py
spotify_gender_ex/replacement_table.py
spotify_gender_ex/workdir.py
spotify_gender_ex/lib/Apktool_License.md
spotify_gender_ex/lib/Uber_APK_Signer_License.md
spotify_gender_ex/lib/apktool.jar
spotify_gender_ex/lib/uber-apk-signer-1.2.1.jar
spotify_gender_ex/res/credits.html
spotify_gender_ex/res/replacements.json
Spotify_Gender_Ex-3.3.0.dist-info/LICENSE
Spotify_Gender_Ex-3.3.0.dist-info/METADATA
Spotify_Gender_Ex-3.3.0.dist-info/WHEEL
Spotify_Gender_Ex-3.3.0.dist-info/entry_points.txt
Spotify_Gender_Ex-3.3.0.dist-info/top_level.txt
Spotify_Gender_Ex-3.3.0.dist-info/RECORD
