Metadata-Version: 2.1
Name: Spotify-Gender-Ex
Version: 3.3.0
Summary: Ein kleines Tool, das die Gendersternchen (z.B. Künstler*innen) aus der Spotify-App für Android entfernt.
Home-page: https://github.com/Theta-Dev/Spotify-Gender-Ex
Author: ThetaDev
License: MIT License
Platform: UNKNOWN
Classifier: License :: OSI Approved :: MIT License
Classifier: Programming Language :: Python :: 3
Classifier: Programming Language :: Python :: 3.7
Classifier: Programming Language :: Python :: 3.8
Classifier: Programming Language :: Python :: 3.9
License-File: LICENSE
Requires-Dist: click
Requires-Dist: tqdm
Requires-Dist: importlib-resources
Requires-Dist: pyyaml
Requires-Dist: requests
Requires-Dist: github3.py
Requires-Dist: beautifulsoup4
Provides-Extra: selenium
Requires-Dist: selenium ; extra == 'selenium'
